PyFourier/__init__.py
PyFourier/fourier1D.py
PyFourier-0.0.2.1.dist-info/LICENSE
PyFourier-0.0.2.1.dist-info/METADATA
PyFourier-0.0.2.1.dist-info/WHEEL
PyFourier-0.0.2.1.dist-info/top_level.txt
PyFourier-0.0.2.1.dist-info/RECORD
