Metadata-Version: 2.1
Name: PyFourier
Version: 0.0.2.1
Summary: 'A module for visualizing Fourier transform and its properties'
Home-page: https://github.com/LopezBanos/PyFourier
Author: Sergio Lopez Banos
Author-email: sergioloba98@gmail.com
License: UNKNOWN
Project-URL: Bug Tracker, https://github.com/LopezBanos/PyFourier/issues
Platform: UNKNOWN
Classifier: Programming Language :: Python :: 3
Classifier: License :: OSI Approved :: BSD License
Classifier: Operating System :: OS Independent
Requires-Python: >=3.7
License-File: LICENSE
